{
  "generatedAt": "2026-07-20T13:26:40.227Z",
  "dbPath": "reports/excel-snapshot-audit/local-sample.sqlite",
  "findings": {
    "currentIdentityDuplicates": [],
    "updateAndExcludeSameSnapshot": [],
    "dateMinusOneDayCandidates": [],
    "excludedDocumentsInSets": [],
    "abandonedSnapshots": [],
    "moveAuditWithoutMovementLog": [],
    "excelRestoreCandidates": [],
    "snapshotCountMismatchCandidates": []
  },
  "summary": {
    "currentIdentityDuplicates": 0,
    "updateAndExcludeSameSnapshot": 0,
    "dateMinusOneDayCandidates": 0,
    "excludedDocumentsInSets": 0,
    "abandonedSnapshots": 0,
    "moveAuditWithoutMovementLog": 0,
    "excelRestoreCandidates": 0,
    "snapshotCountMismatchCandidates": 0
  }
}
